proxy_session/__init__.py
proxy_session/session.py
Proxy_Session-0.1.1.dist-info/LICENSE
Proxy_Session-0.1.1.dist-info/METADATA
Proxy_Session-0.1.1.dist-info/WHEEL
Proxy_Session-0.1.1.dist-info/top_level.txt
Proxy_Session-0.1.1.dist-info/RECORD
