Metadata-Version: 2.1
Name: Proxy-Session
Version: 0.1.1
Summary: Proxy-Session is a python module, helps to make a reliable proxy request to a HTTP server.         Current version of this module is 0.1.1     
Home-page: https://github.com/antaripchatterjee/Proxy-Session
Author: Antarip Chatterjee
Author-email: antarip.chatterjee22@gmail.com
License: MIT
Platform: UNKNOWN
Classifier: License :: OSI Approved :: MIT License
Classifier: Operating System :: Microsoft :: Windows
Classifier: Operating System :: Unix
Classifier: Operating System :: POSIX :: Linux
Classifier: Operating System :: MacOS
Classifier: Operating System :: OS Independent
Classifier: Programming Language :: Python :: 3.6
Classifier: Environment :: Console
Classifier: Development Status :: 4 - Beta
Classifier: Intended Audience :: Developers
Classifier: Intended Audience :: Education
Classifier: Topic :: Education
Classifier: Topic :: Software Development
Requires-Dist: beautifulsoup4 (==4.9.3)
Requires-Dist: html5lib (==1.1)
Requires-Dist: requests (==2.25.1)
